{
    "macros": [
        "MBED_CONF_APP_MAIN_STACK_SIZE=4096",
        "MBEDTLS_USER_CONFIG_FILE=\"mbedtls_user_config.h\""
    ],
    "target_overrides": {
        "*": {
            "platform.stdio-baud-rate"              : 115200,
            "platform.stdio-convert-newlines"       : true,
            "platform.heap-stats-enabled"           : 1,
            "platform.stack-stats-enabled"          : 1,
            "mbed-trace.enable"                     : null,
            "nsapi.default-wifi-security"           : "WPA_WPA2",
            "nsapi.default-wifi-ssid"               : "\"SSID\"",
            "nsapi.default-wifi-password"           : "\"Password\"",
            "drivers.uart-serial-rxbuf-size"        : 1024,
            "drivers.uart-serial-txbuf-size"        : 1024
        },
        "NUMAKER_PFM_NUC472": {
            "target.network-default-interface-type" : "ETHERNET",
            "my-tlssocket.tls-max-frag-len"         : 4,
            "target.macros_add"                     : ["ESP8266_AT_SEL=ESP8266_AT_EXTERN"]
        },
        "NUMAKER_PFM_M487": {
            "target.network-default-interface-type" : "ETHERNET",
            "my-tlssocket.tls-max-frag-len"         : 4,
            "target.macros_add"                     : ["ESP8266_AT_SEL=ESP8266_AT_EXTERN"]
        },
        "NUMAKER_IOT_M487": {
            "target.network-default-interface-type" : "WIFI",
            "my-tlssocket.tls-max-frag-len"         : 4,
            "target.macros_add"                     : ["ESP8266_AT_SEL=ESP8266_AT_ONBOARD"]
        },
        "NUMAKER_PFM_M2351": {
            "target.network-default-interface-type" : "WIFI",
            "my-tlssocket.tls-max-frag-len"         : 4,

            "target.mbed_rom_start"                 : "0x10020000",
            "target.mbed_rom_size"                  : "0x60000",
            "target.mbed_ram_start"                 : "0x30004000",
            "target.mbed_ram_size"                  : "0x14000",

            "target.macros_add"                     : ["ESP8266_AT_SEL=ESP8266_AT_ONBOARD"]
        }
    }
}
